Workbook

Sheet Summary
A1: BIG SUMMARY
A3: Data Centre Allocation: | B3: Scotland
A4: Total Capacity [GW]: | B4: 4
A5: Flexibility: | B5: 0.1
A6: x_CFE: | B6: 0.03
A7: Total Green Energy | B7: =SUMIFS(Inflexible!$D$2:$D$32,Inflexible!$B$2:$B$32,"Solar PV")+SUMIFS(Inflexible!$D$2:$D$32,Inflexible!$B$2:$B$32,"Offshore Wind")+SUMIFS(Inflexible!$D$2:$D$32,Inflexible!$B$2:$B$32,"Onshore Wind")+SUMIFS(Inflexible!$D$2:$D$32,Inflexible!$B$2:$B$32,"Large Hydro") -> 123182.66
A8: Total Storage | B8: =SUMIFS(Inflexible!$D$2:$D$32,Inflexible!$B$2:$B$32,"Battery Storage")+SUMIFS(Inflexible!$D$2:$D$32,Inflexible!$B$2:$B$32,"Domestic Battery Storage")+SUMIFS(Inflexible!$D$2:$D$32,Inflexible!$B$2:$B$32,"Liquid Air Energy Storage")+SUMIFS(Inflexible!$D$2:$D$32,Inflexible!$B$2:$B$32,"Pumped Storage Hydroelectricity")+SUMIFS(Inflexible!$D$2:$D$32,Inflexible!$B$2:$B$32,"Hydrogen Gas") -> 79855.683
B10: Inflexible | C10: Temporal | D10: Spatial | E10: Both | F10: CFE | G10: CFE + Both
A11: Total Green Energy Curtailment | B11: =SUMIFS(Inflexible!$J$2:$J$34,Inflexible!$B$2:$B$34, "Solar PV")+SUMIFS(Inflexible!$J$2:$J$34,Inflexible!$B$2:$B$34, "Offshore Wind")+SUMIFS(Inflexible!$J$2:$J$34,Inflexible!$B$2:$B$34, "Onshore Wind")+SUMIFS(Inflexible!$J$2:$J$34,Inflexible!$B$2:$B$34, "Large Hydro")+SUMIFS(Inflexible!$J$2:$J$34,Inflexible!$B$2:$B$34, "Marine Energy") -> 11412216 | C11: =SUMIFS(Temporal!$J$2:$J$34,Inflexible!$B$2:$B$34, "Solar PV")+SUMIFS(Temporal!$J$2:$J$34,Temporal!$B$2:$B$34, "Offshore Wind")+SUMIFS(Temporal!$J$2:$J$34,Temporal!$B$2:$B$34, "Onshore Wind")+SUMIFS(Temporal!$J$2:$J$34,Temporal!$B$2:$B$34, "Large Hydro")+SUMIFS(Inflexible!$J$2:$J$34,Temporal!$B$2:$B$34, "Marine Energy") -> 11383408 | D11: =SUMIFS(Spatial!$J$2:$J$34,Spatial!$B$2:$B$34, "Solar PV")+SUMIFS(Spatial!$J$2:$J$34,Spatial!$B$2:$B$34, "Offshore Wind")+SUMIFS(Spatial!$J$2:$J$34,Spatial!$B$2:$B$34, "Onshore Wind")+SUMIFS(Spatial!$J$2:$J$34,Spatial!$B$2:$B$34, "Large Hydro")+SUMIFS(Spatial!$J$2:$J$34,Spatial!$B$2:$B$34, "Marine Energy") -> 11631525 | E11: =SUMIFS(Both!$J$2:$J$35,Both!$B$2:$B$35, "Solar PV")+SUMIFS(Both!$J$2:$J$35,Both!$B$2:$B$35, "Offshore Wind")+SUMIFS(Both!$J$2:$J$35,Both!$B$2:$B$35, "Onshore Wind")+SUMIFS(Both!$J$2:$J$35,Both!$B$2:$B$35, "Large Hydro")+SUMIFS(Both!$J$2:$J$35,Both!$B$2:$B$35, "Marine Energy") -> 11705346 | F11: =SUMIFS(CFE!$J$2:$J$34,CFE!$B$2:$B$34, "Solar PV")+SUMIFS(CFE!$J$2:$J$34,CFE!$B$2:$B$34, "Offshore Wind")+SUMIFS(CFE!$J$2:$J$34,CFE!$B$2:$B$34, "Onshore Wind")+SUMIFS(CFE!$J$2:$J$34,CFE!$B$2:$B$34, "Large Hydro")+SUMIFS(CFE!$J$2:$J$34,CFE!$B$2:$B$34, "Marine Energy") -> 11295554 | G11: =SUMIFS(CFE_both!$J$2:$J$35,CFE_both!$B$2:$B$35, "Solar PV")+SUMIFS(CFE_both!$J$2:$J$35,CFE_both!$B$2:$B$35, "Offshore Wind")+SUMIFS(CFE_both!$J$2:$J$35,CFE_both!$B$2:$B$35, "Onshore Wind")+SUMIFS(CFE_both!$J$2:$J$35,CFE_both!$B$2:$B$35, "Large Hydro")+SUMIFS(CFE_both!$J$2:$J$35,CFE_both!$B$2:$B$35, "Marine Energy") -> 11608799
A12: Total Wind Offshore Curtailment | B12: =SUMIFS(Inflexible!$J$2:$J$34,Inflexible!$B$2:$B$34, "Offshore Wind") -> 6642041 | C12: =SUMIFS(Temporal!$J$2:$J$34,Temporal!$B$2:$B$34, "Offshore Wind") -> 6615477 | D12: =SUMIFS(Spatial!$J$2:$J$34,Spatial!$B$2:$B$34, "Offshore Wind") -> 6930775 | E12: =SUMIFS(Both!$J$2:$J$35,Both!$B$2:$B$35, "Offshore Wind") -> 6816858 | F12: =SUMIFS(CFE!$J$2:$J$34,CFE!$B$2:$B$34, "Offshore Wind") -> 6546350 | G12: =SUMIFS(CFE_both!$J$2:$J$35,CFE_both!$B$2:$B$35, "Offshore Wind") -> 6855179
A13: Total Wind Onshore Curtailment | B13: =SUMIFS(Inflexible!$J$2:$J$34,Inflexible!$B$2:$B$34, "Onshore Wind") -> 3145740 | C13: =SUMIFS(Temporal!$J$2:$J$34,Temporal!$B$2:$B$34, "Onshore Wind") -> 2920392 | D13: =SUMIFS(Spatial!$J$2:$J$34,Spatial!$B$2:$B$34, "Onshore Wind") -> 3064199 | E13: =SUMIFS(Both!$J$2:$J$35,Both!$B$2:$B$35, "Onshore Wind") -> 3168929 | F13: =SUMIFS(CFE!$J$2:$J$34,CFE!$B$2:$B$34, "Onshore Wind") -> 3116530 | G13: =SUMIFS(CFE_both!$J$2:$J$35,CFE_both!$B$2:$B$35, "Onshore Wind") -> 3078499
A14: Total Solar PV Curtailment | B14: =SUMIFS(Inflexible!$J$2:$J$34,Inflexible!$B$2:$B$34, "Solar PV") -> 1348080 | C14: =SUMIFS(Temporal!$J$2:$J$34,Temporal!$B$2:$B$34, "Solar PV") -> 1570499 | D14: =SUMIFS(Spatial!$J$2:$J$34,Spatial!$B$2:$B$34, "Solar PV") -> 1344158 | E14: =SUMIFS(Both!$J$2:$J$35,Both!$B$2:$B$35, "Solar PV") -> 1412444 | F14: =SUMIFS(CFE!$J$2:$J$34,CFE!$B$2:$B$34, "Solar PV") -> 1349598 | G14: =SUMIFS(CFE_both!$J$2:$J$35,CFE_both!$B$2:$B$35, "Solar PV") -> 1380241
A15: DC Cost | B15: =-Inflexible!$M$26 -> 14118940 | C15: =-Temporal!$M$27 -> 14097900 | D15: =-Spatial!$M$27 -> 14124690 | E15: =-Both!$M$28 -> 14080300 | F15: =-CFE!$M$26 -> 14118940 | G15: =-CFE_both!$M$28 -> 13965940
A16: Network objective | B16: 81875276 | C16: 81501280 | D16: 81690990 | E16: 81316954 | F16: 81875276 | G16: 80486835

Sheet Inflexible
C1: Optimal Capacity | D1: Installed Capacity | E1: Supply | F1: Withdrawal | G1: Energy Balance | H1: Transmission | I1: Capacity Factor | J1: Curtailment | K1: Capital Expenditure | L1: Operational Expenditure | M1: Revenue | N1: Market Value
A2: Generator | B2: Advanced Biofuel | C2: 372.43929 | D2: 372.43929 | E2: 0 | F2: 0 | G2: 0 | H2: 0 | I2: 0 | J2: 813779.8 | K2: 0 | L2: 0 | M2: 0 | N2: NaN
B3: Biogas | C3: 1642.8915 | D3: 1642.8915 | E3: 0 | F3: 0 | G3: 0 | H3: 0 | I3: 0 | J3: 3589718 | K3: 0 | L3: 0 | M3: 0 | N3: NaN
B4: Biomass | C4: 9185.8067 | D4: 9185.8067 | E4: 0 | F4: 0 | G4: 0 | H4: 0 | I4: 0 | J4: 20070990 | K4: 0 | L4: 0 | M4: 0 | N4: NaN
B5: Combined Cycle Gas Turbine | C5: 23586 | D5: 23586 | E5: 0 | F5: 0 | G5: 0 | H5: 0 | I5: 0 | J5: 51535410 | K5: 0 | L5: 0 | M5: 0 | N5: NaN
B6: Combined Heat & Power | C6: 3534.036 | D6: 3534.036 | E6: 0 | F6: 0 | G6: 0 | H6: 0 | I6: 0 | J6: 7721869 | K6: 0 | L6: 0 | M6: 0 | N6: NaN
B7: European Imports | C7: 13695 | D7: 13695 | E7: 3571751 | F7: 0 | G7: 3571751 | H7: 0 | I7: 0.119362 | J7: 26351820 | K7: 0 | L7: 40697210 | M7: 40697210 | N7: 11.394189
B8: Gas Engine | C8: 4067.294 | D8: 4067.294 | E8: 0 | F8: 0 | G8: 0 | H8: 0 | I8: 0 | J8: 8887037 | K8: 0 | L8: 0 | M8: 0 | N8: NaN
B9: Geothermal | C9: 11 | D9: 11 | E9: 4643.509 | F9: 0 | G9: 4643.509 | H9: 0 | I9: 0.193198 | J9: 19391.49 | K9: 0 | L9: 57858.12 | M9: 99256.85 | N9: 21.375356
B10: Landfill Gas | C10: 834.51107 | D10: 834.51107 | E10: 1327.783 | F10: 0 | G10: 1327.783 | H10: 0 | I10: 0.000728 | J10: 1822079 | K10: 0 | L10: 71700.3 | M10: 71876.93 | N10: 54.133129
B11: Large Hydro | C11: 1897.296 | D11: 1897.296 | E11: 1417072 | F11: 0 | G11: 1417072 | H11: 0 | I11: 0.341826 | J11: 241164.7 | K11: 0 | L11: 0 | M11: 9471836 | N11: 6.684089
B12: Load Shedding | C12: 48629.191 | D12: 48629.191 | E12: 0 | F12: 0 | G12: 0 | H12: 0 | I12: 0 | J12: 52178340 | K12: 0 | L12: 0 | M12: 0 | N12: NaN
B13: Marine Energy | C13: 254.358 | D13: 254.358 | E13: 238579.7 | F13: 0 | G13: 238579.7 | H13: 0 | I13: 0.429276 | J13: 35189.86 | K13: 0 | L13: 0 | M13: 2000389 | N13: 8.384572
B14: Nuclear | C14: 4570 | D14: 4570 | E14: 4061356 | F14: 0 | G14: 4061356 | H14: 0 | I14: 0.406727 | J14: 5924094 | K14: 0 | L14: 40613560 | M14: 68047740 | N14: 16.754933
B15: Offshore Wind | C15: 53544.202 | D15: 53544.202 | E15: 25472810 | F15: 0 | G15: 25472810 | H15: 0 | I15: 0.217727 | J15: 6642041 | K15: 0 | L15: 0 | M15: 102405100 | N15: 4.020174
B16: Oil | C16: 78.5 | D16: 78.5 | E16: 0 | F16: 0 | G16: 0 | H16: 0 | I16: 0 | J16: 171522.5 | K16: 0 | L16: 0 | M16: 0 | N16: NaN
B17: Onshore Wind | C17: 27270.741 | D17: 27270.741 | E17: 11189390 | F17: 0 | G17: 11189390 | H17: 0 | I17: 0.187784 | J17: 3145740 | K17: 0 | L17: 0 | M17: 42150350 | N17: 3.766992
B18: Open Cycle Gas Turbine | C18: 3662.89 | D18: 3662.89 | E18: 0 | F18: 0 | G18: 0 | H18: 0 | I18: 0 | J18: 8003415 | K18: 0 | L18: 0 | M18: 0 | N18: NaN
B19: Sewage Gas | C19: 55.81939 | D19: 55.81939 | E19: 0 | F19: 0 | G19: 0 | H19: 0 | I19: 0 | J19: 121965.4 | K19: 0 | L19: 0 | M19: 0 | N19: NaN
B20: Solar PV | C20: 40470.422 | D20: 40470.422 | E20: 13217460 | F20: 0 | G20: 13217460 | H20: 0 | I20: 0.149472 | J20: 1348080 | K20: 0 | L20: 0 | M20: 90278670 | N20: 6.830258
B21: Waste to Energy | C21: 4643.178 | D21: 4643.178 | E21: 0 | F21: 0 | G21: 0 | H21: 0 | I21: 0 | J21: 10145340 | K21: 0 | L21: 0 | M21: 0 | N21: NaN
A22: Line | B22: AC | C22: 230800 | D22: 230800 | E22: 35023140 | F22: 21829910 | G22: 13193230 | H22: -13193230 | I22: 0.112737 | J22: 0 | K22: 0 | L22: 0 | M22: 135731500 | N22: 2.38741
A23: Link | B23: DC | C23: 12450 | D23: 12450 | E23: 9549085 | F23: 5885750 | G23: 3663335 | H23: -3663335 | I23: 0.567389 | J23: 30866580 | K23: 0 | L23: 0 | M23: 70784100 | N23: 4.585997
B24: Electrolysis | C24: 3653.0948 | D24: 3653.0948 | E24: 0 | F24: 134827.9 | G24: -134827.9 | H24: 0 | I24: 0.016891 | J24: 7847184 | K24: 0 | L24: 0 | M24: 0 | N24: NaN
B25: H2 Power Generation | C25: 278.381 | D25: 278.381 | E25: 0 | F25: 86990.56 | G25: -86990.56 | H25: 0 | I25: 0.143015 | J25: 521271.9 | K25: 0 | L25: 434952.8 | M25: 0 | N25: NaN
A26: Load | B26: Data Centre | C26: 0 | D26: 0 | E26: 0 | F26: 1877543 | G26: -1877543 | H26: 0 | I26: NaN | J26: 0 | K26: 0 | L26: 0 | M26: -14118940 | N26: -7.519904
B27: Electricity | C27: 0 | D27: 0 | E27: 0 | F27: 52178340 | G27: -52178340 | H27: 0 | I27: NaN | J27: 0 | K27: 0 | L27: 0 | M27: -411891500 | N27: -7.893917
A28: StorageUnit | B28: Battery Storage | C28: 26471.973 | D28: 26471.973 | E28: 2729198 | F28: 6114821 | G28: -3385623 | H28: 0 | I28: 0.152902 | J28: 61226880 | K28: 0 | L28: 0 | M28: 16741690 | N28: 1.892996
B29: Domestic Battery Storage | C29: 857.708 | D29: 857.708 | E29: 142784.8 | F29: 270758.7 | G29: -127974 | H29: 0 | I29: 0.220663 | J29: 2002066 | K29: 0 | L29: 0 | M29: 548921.5 | N29: 1.327361
B30: Liquid Air Energy Storage | C30: 457.994 | D30: 457.994 | E30: 31042.26 | F30: 250613 | G30: -219570.7 | H30: 0 | I30: 0.281453 | J30: 1220288 | K30: 0 | L30: 0 | M30: 549749.4 | N30: 1.951852
B31: Pumped Storage Hydroelectricity | C31: 5300 | D31: 5300 | E31: 846578.6 | F31: 2232174 | G31: -1385595 | H31: 0 | I31: 0.265857 | J31: 12966100 | K31: 0 | L31: 0 | M31: 10545950 | N31: 3.425396
A32: Store | B32: Hydrogen Gas | C32: 46768.008 | D32: 46768.008 | E32: 86120.38 | F32: 93509.37 | G32: -7388.984 | H32: 0 | I32: 0.723077 | J32: 0 | K32: 0 | L32: 0 | M32: 0 | N32: NaN

Sheet Temporal
C1: Optimal Capacity | D1: Installed Capacity | E1: Supply | F1: Withdrawal | G1: Energy Balance | H1: Transmission | I1: Capacity Factor | J1: Curtailment | K1: Capital Expenditure | L1: Operational Expenditure | M1: Revenue | N1: Market Value
A2: Generator | B2: Advanced Biofuel | C2: 372.4393 | D2: 372.4393 | E2: 0 | F2: 0 | G2: 0 | H2: 0 | I2: 0 | J2: 813779.8 | K2: 0 | L2: 0 | M2: 0 | N2: NaN
B3: Biogas | C3: 1642.892 | D3: 1642.892 | E3: 0 | F3: 0 | G3: 0 | H3: 0 | I3: 0 | J3: 3589718 | K3: 0 | L3: 0 | M3: 0 | N3: NaN
B4: Biomass | C4: 9185.807 | D4: 9185.807 | E4: 0 | F4: 0 | G4: 0 | H4: 0 | I4: 0 | J4: 20070990 | K4: 0 | L4: 0 | M4: 0 | N4: NaN
B5: Combined Cycle Gas Turbine | C5: 23586 | D5: 23586 | E5: 0 | F5: 0 | G5: 0 | H5: 0 | I5: 0 | J5: 51535410 | K5: 0 | L5: 0 | M5: 0 | N5: NaN
B6: Combined Heat & Power | C6: 3534.036 | D6: 3534.036 | E6: 0 | F6: 0 | G6: 0 | H6: 0 | I6: 0 | J6: 7721869 | K6: 0 | L6: 0 | M6: 0 | N6: NaN
B7: European Imports | C7: 13695 | D7: 13695 | E7: 3544252 | F7: 0 | G7: 3544252 | H7: 0 | I7: 0.118443 | J7: 26379320 | K7: 0 | L7: 40348850 | M7: 40348850 | N7: 11.384308
B8: Gas Engine | C8: 4067.294 | D8: 4067.294 | E8: 0 | F8: 0 | G8: 0 | H8: 0 | I8: 0 | J8: 8887037 | K8: 0 | L8: 0 | M8: 0 | N8: NaN
B9: Geothermal | C9: 11 | D9: 11 | E9: 4559.605 | F9: 0 | G9: 4559.605 | H9: 0 | I9: 0.189707 | J9: 19475.39 | K9: 0 | L9: 56812.68 | M9: 97821.15 | N9: 21.453819
B10: Landfill Gas | C10: 834.5111 | D10: 834.5111 | E10: 985.9801 | F10: 0 | G10: 985.9801 | H10: 0 | I10: 0.000541 | J10: 1822421 | K10: 0 | L10: 53242.93 | M10: 53415.83 | N10: 54.175313
B11: Large Hydro | C11: 1897.296 | D11: 1897.296 | E11: 1416387 | F11: 0 | G11: 1416387 | H11: 0 | I11: 0.341661 | J11: 241849.9 | K11: 0 | L11: 0 | M11: 9439016 | N11: 6.664151
B12: Load Shedding | C12: 48629.19 | D12: 48629.19 | E12: 0 | F12: 0 | G12: 0 | H12: 0 | I12: 0 | J12: 52178340 | K12: 0 | L12: 0 | M12: 0 | N12: NaN
B13: Marine Energy | C13: 254.358 | D13: 254.358 | E13: 237103 | F13: 0 | G13: 237103 | H13: 0 | I13: 0.426619 | J13: 36666.59 | K13: 0 | L13: 0 | M13: 1996544 | N13: 8.420578
B14: Nuclear | C14: 4570 | D14: 4570 | E14: 4060086 | F14: 0 | G14: 4060086 | H14: 0 | I14: 0.4066 | J14: 5925364 | K14: 0 | L14: 40600860 | M14: 67848500 | N14: 16.7111
B15: Offshore Wind | C15: 53544.2 | D15: 53544.2 | E15: 25499370 | F15: 0 | G15: 25499370 | H15: 0 | I15: 0.217954 | J15: 6615477 | K15: 0 | L15: 0 | M15: 102437800 | N15: 4.017268
B16: Oil | C16: 78.5 | D16: 78.5 | E16: 0 | F16: 0 | G16: 0 | H16: 0 | I16: 0 | J16: 171522.5 | K16: 0 | L16: 0 | M16: 0 | N16: NaN
B17: Onshore Wind | C17: 27270.74 | D17: 27270.74 | E17: 11414740 | F17: 0 | G17: 11414740 | H17: 0 | I17: 0.191566 | J17: 2920392 | K17: 0 | L17: 0 | M17: 42126150 | N17: 3.690504
B18: Open Cycle Gas Turbine | C18: 3662.89 | D18: 3662.89 | E18: 0 | F18: 0 | G18: 0 | H18: 0 | I18: 0 | J18: 8003415 | K18: 0 | L18: 0 | M18: 0 | N18: NaN
B19: Sewage Gas | C19: 55.81939 | D19: 55.81939 | E19: 0 | F19: 0 | G19: 0 | H19: 0 | I19: 0 | J19: 121965.4 | K19: 0 | L19: 0 | M19: 0 | N19: NaN
B20: Solar PV | C20: 40470.42 | D20: 40470.42 | E20: 12995040 | F20: 0 | G20: 12995040 | H20: 0 | I20: 0.146956 | J20: 1570499 | K20: 0 | L20: 0 | M20: 90210550 | N20: 6.941921
B21: Waste to Energy | C21: 4643.178 | D21: 4643.178 | E21: 0 | F21: 0 | G21: 0 | H21: 0 | I21: 0 | J21: 10145340 | K21: 0 | L21: 0 | M21: 0 | N21: NaN
A22: Line | B22: AC | C22: 230800 | D22: 230800 | E22: 35364110 | F22: 21540860 | G22: 13823250 | H22: -13823250 | I22: 0.11284 | J22: 0 | K22: 0 | L22: 0 | M22: 133319500 | N22: 2.342845
A23: Link | B23: DC | C23: 12450 | D23: 12450 | E23: 9582992 | F23: 5947862 | G23: 3635130 | H23: -3635130 | I23: 0.570919 | J23: 30838380 | K23: 0 | L23: 0 | M23: 70335700 | N23: 4.528772
B24: DSM | C24: 26000000 | D24: 26000000 | E24: 0 | F24: 109235.3 | G24: -109235.3 | H24: 0 | I24: 2e-06 | J24: 56809890000 | K24: 0 | L24: 1.09235 | M24: -882868.5 | N24: -8.082266
B25: Electrolysis | C25: 3653.095 | D25: 3653.095 | E25: 0 | F25: 131416.1 | G25: -131416.1 | H25: 0 | I25: 0.016464 | J25: 7850596 | K25: 0 | L25: 0 | M25: 0 | N25: NaN
B26: H2 Power Generation | C26: 278.381 | D26: 278.381 | E26: 0 | F26: 88302.75 | G26: -88302.75 | H26: 0 | I26: 0.145172 | J26: 519959.7 | K26: 0 | L26: 441513.7 | M26: 0 | N26: NaN
A27: Load | B27: Data Centre | C27: 0 | D27: 0 | E27: 0 | F27: 1877543 | G27: -1877543 | H27: 0 | I27: NaN | J27: 0 | K27: 0 | L27: 0 | M27: -14097900 | N27: -7.508697
B28: Electricity | C28: 0 | D28: 0 | E28: 0 | F28: 52178340 | G28: -52178340 | H28: 0 | I28: NaN | J28: 0 | K28: 0 | L28: 0 | M28: -411303000 | N28: -7.88264
A29: StorageUnit | B29: Battery Storage | C29: 26471.97 | D29: 26471.97 | E29: 2741421 | F29: 6133689 | G29: -3392268 | H29: 0 | I29: 0.153439 | J29: 61233530 | K29: 0 | L29: 0 | M29: 16580990 | N29: 1.868257
B30: Domestic Battery Storage | C30: 857.708 | D30: 857.708 | E30: 143178.5 | F30: 273329.3 | G30: -130150.8 | H30: 0 | I30: 0.222245 | J30: 2004243 | K30: 0 | L30: 0 | M30: 543694.1 | N30: 1.305364
B31: Liquid Air Energy Storage | C31: 457.994 | D31: 457.994 | E31: 31291.71 | F31: 253075.2 | G31: -221783.5 | H31: 0 | I31: 0.284163 | J31: 1222500 | K31: 0 | L31: 0 | M31: 544677.8 | N31: 1.915405
B32: Pumped Storage Hydroelectricity | C32: 5300 | D32: 5300 | E32: 863060.3 | F32: 2239119 | G32: -1376059 | H32: 0 | I32: 0.26788 | J32: 12956560 | K32: 0 | L32: 0 | M32: 10420020 | N32: 3.358936
A33: Store | B33: DSM | C33: 13000000 | D33: 13000000 | E33: 54617.63 | F33: 54617.63 | G33: 0 | H33: 0 | I33: 0.999926 | J33: 0 | K33: 0 | L33: 0 | M33: 0 | N33: NaN
B34: Hydrogen Gas | C34: 46768.01 | D34: 46768.01 | E34: 86530.8 | F34: 90219.3 | G34: -3688.498 | H34: 0 | I34: 0.360952 | J34: 0 | K34: 0 | L34: 0 | M34: 0 | N34: NaN

Sheet Spatial
C1: Optimal Capacity | D1: Installed Capacity | E1: Supply | F1: Withdrawal | G1: Energy Balance | H1: Transmission | I1: Capacity Factor | J1: Curtailment | K1: Capital Expenditure | L1: Operational Expenditure | M1: Revenue | N1: Market Value
A2: Generator | B2: Advanced Biofuel | C2: 372.4393 | D2: 372.4393 | E2: 0 | F2: 0 | G2: 0 | H2: 0 | I2: 0 | J2: 813779.8 | K2: 0 | L2: 0 | M2: 0 | N2: NaN
B3: Biogas | C3: 1642.892 | D3: 1642.892 | E3: 0 | F3: 0 | G3: 0 | H3: 0 | I3: 0 | J3: 3589718 | K3: 0 | L3: 0 | M3: 0 | N3: NaN
B4: Biomass | C4: 9185.807 | D4: 9185.807 | E4: 0 | F4: 0 | G4: 0 | H4: 0 | I4: 0 | J4: 20070990 | K4: 0 | L4: 0 | M4: 0 | N4: NaN
B5: Combined Cycle Gas Turbine | C5: 23586 | D5: 23586 | E5: 0 | F5: 0 | G5: 0 | H5: 0 | I5: 0 | J5: 51535410 | K5: 0 | L5: 0 | M5: 0 | N5: NaN
B6: Combined Heat & Power | C6: 3534.036 | D6: 3534.036 | E6: 0 | F6: 0 | G6: 0 | H6: 0 | I6: 0 | J6: 7721869 | K6: 0 | L6: 0 | M6: 0 | N6: NaN
B7: European Imports | C7: 13695 | D7: 13695 | E7: 3541053 | F7: 0 | G7: 3541053 | H7: 0 | I7: 0.1183365 | J7: 26382520 | K7: 0 | L7: 40561730 | M7: 40561730 | N7: 11.454711
B8: Gas Engine | C8: 4067.294 | D8: 4067.294 | E8: 0 | F8: 0 | G8: 0 | H8: 0 | I8: 0 | J8: 8887037 | K8: 0 | L8: 0 | M8: 0 | N8: NaN
B9: Geothermal | C9: 11 | D9: 11 | E9: 4643.509 | F9: 0 | G9: 4643.509 | H9: 0 | I9: 0.1931982 | J9: 19391.49 | K9: 0 | L9: 57858.12 | M9: 99417.85 | N9: 21.410026
B10: Landfill Gas | C10: 834.5111 | D10: 834.5111 | E10: 1373.642 | F10: 0 | G10: 1373.642 | H10: 0 | I10: 0.0007533393 | J10: 1822033 | K10: 0 | L10: 74176.66 | M10: 74347.88 | N10: 54.124565
B11: Large Hydro | C11: 1897.296 | D11: 1897.296 | E11: 1399606 | F11: 0 | G11: 1399606 | H11: 0 | I11: 0.3376132 | J11: 258630.3 | K11: 0 | L11: 0 | M11: 9528779 | N11: 6.808185
B12: Load Shedding | C12: 48629.19 | D12: 48629.19 | E12: 0 | F12: 0 | G12: 0 | H12: 0 | I12: 0 | J12: 52178340 | K12: 0 | L12: 0 | M12: 0 | N12: NaN
B13: Marine Energy | C13: 254.358 | D13: 254.358 | E13: 240007.2 | F13: 0 | G13: 240007.2 | H13: 0 | I13: 0.4318444 | J13: 33762.4 | K13: 0 | L13: 0 | M13: 2004213 | N13: 8.350641
B14: Nuclear | C14: 4570 | D14: 4570 | E14: 4053639 | F14: 0 | G14: 4053639 | H14: 0 | I14: 0.4059545 | J14: 5931811 | K14: 0 | L14: 40536390 | M14: 67962270 | N14: 16.765745
B15: Offshore Wind | C15: 53544.2 | D15: 53544.2 | E15: 25184070 | F15: 0 | G15: 25184070 | H15: 0 | I15: 0.2152594 | J15: 6930775 | K15: 0 | L15: 0 | M15: 102429300 | N15: 4.067225
B16: Oil | C16: 78.5 | D16: 78.5 | E16: 0 | F16: 0 | G16: 0 | H16: 0 | I16: 0 | J16: 171522.5 | K16: 0 | L16: 0 | M16: 0 | N16: NaN
B17: Onshore Wind | C17: 27270.74 | D17: 27270.74 | E17: 11270940 | F17: 0 | G17: 11270940 | H17: 0 | I17: 0.1891523 | J17: 3064199 | K17: 0 | L17: 0 | M17: 42266950 | N17: 3.750084
B18: Open Cycle Gas Turbine | C18: 3662.89 | D18: 3662.89 | E18: 0 | F18: 0 | G18: 0 | H18: 0 | I18: 0 | J18: 8003415 | K18: 0 | L18: 0 | M18: 0 | N18: NaN
B19: Sewage Gas | C19: 55.81939 | D19: 55.81939 | E19: 0 | F19: 0 | G19: 0 | H19: 0 | I19: 0 | J19: 121965.4 | K19: 0 | L19: 0 | M19: 0 | N19: NaN
B20: Solar PV | C20: 40470.42 | D20: 40470.42 | E20: 13221380 | F20: 0 | G20: 13221380 | H20: 0 | I20: 0.149516 | J20: 1344158 | K20: 0 | L20: 0 | M20: 90280280 | N20: 6.828354
B21: Waste to Energy | C21: 4643.178 | D21: 4643.178 | E21: 0 | F21: 0 | G21: 0 | H21: 0 | I21: 0 | J21: 10145340 | K21: 0 | L21: 0 | M21: 0 | N21: NaN
A22: Line | B22: AC | C22: 230800 | D22: 230800 | E22: 34790030 | F22: 21544090 | G22: 13245940 | H22: -13245940 | I22: 0.111708 | J22: 0 | K22: 0 | L22: 0 | M22: 133333100 | N22: 2.366827
A23: Link | B23: DC | C23: 12450 | D23: 12450 | E23: 9526165 | F23: 5894316 | G23: 3631849 | H23: -3631849 | I23: 0.5668617 | J23: 30835100 | K23: 0 | L23: 0 | M23: 70623860 | N23: 4.579874
B24: Electrolysis | C24: 3653.095 | D24: 3653.095 | E24: 0 | F24: 137504.4 | G24: -137504.4 | H24: 0 | I24: 0.01722679 | J24: 7844508 | K24: 0 | L24: 0 | M24: 0 | N24: NaN
B25: H2 Power Generation | C25: 278.381 | D25: 278.381 | E25: 0 | F25: 92166.44 | G25: -92166.44 | H25: 0 | I25: 0.1515241 | J25: 516096 | K25: 0 | L25: 460832.2 | M25: 0 | N25: NaN
B26: Virtual Link | C26: 156000000 | D26: 156000000 | E26: 0 | F26: 16445.91 | G26: -16445.91 | H26: 16445.91 | I26: 4.824827e-08 | J26: 340860000000 | K26: 0 | L26: 0.16446 | M26: -86144.25 | N26: -5.238037
A27: Load | B27: Data Centre | C27: 0 | D27: 0 | E27: 0 | F27: 1877543 | G27: -1877543 | H27: 0 | I27: NaN | J27: 0 | K27: 0 | L27: 0 | M27: -14124690 | N27: -7.522966
B28: Electricity | C28: 0 | D28: 0 | E28: 0 | F28: 52178340 | G28: -52178340 | H28: 0 | I28: NaN | J28: 0 | K28: 0 | L28: 0 | M28: -411818900 | N28: -7.892527
A29: StorageUnit | B29: Battery Storage | C29: 26471.97 | D29: 26471.97 | E29: 3422228 | F29: 6657994 | G29: -3235766 | H29: 0 | I29: 0.1742739 | J29: 61077030 | K29: 0 | L29: 0 | M29: 16733650 | N29: 1.660048
B30: Domestic Battery Storage | C30: 857.708 | D30: 857.708 | E30: 178312 | F30: 299158.8 | G30: -120846.8 | H30: 0 | I30: 0.2547745 | J30: 1994939 | K30: 0 | L30: 0 | M30: 548845.8 | N30: 1.149486
B31: Liquid Air Energy Storage | C31: 457.994 | D31: 457.994 | E31: 32601.86 | F31: 245888.6 | G31: -213286.7 | H31: 0 | I31: 0.2782909 | J31: 1214004 | K31: 0 | L31: 0 | M31: 549093.3 | N31: 1.971678
B32: Pumped Storage Hydroelectricity | C32: 5300 | D32: 5300 | E32: 997080.9 | F32: 2287389 | G32: -1290308 | H32: 0 | I32: 0.2836208 | J32: 12870810 | K32: 0 | L32: 0 | M32: 10511430 | N32: 3.200343
A33: Store | B33: Hydrogen Gas | C33: 46768.01 | D33: 46768.01 | E33: 90821.73 | F33: 94908.4 | G33: -4086.671 | H33: 0 | I33: 0.3999165 | J33: 0 | K33: 0 | L33: 0 | M33: 0 | N33: NaN

Sheet Both
C1: Optimal Capacity | D1: Installed Capacity | E1: Supply | F1: Withdrawal | G1: Energy Balance | H1: Transmission | I1: Capacity Factor | J1: Curtailment | K1: Capital Expenditure | L1: Operational Expenditure | M1: Revenue | N1: Market Value
A2: Generator | B2: Advanced Biofuel | C2: 372.4393 | D2: 372.4393 | E2: 0 | F2: 0 | G2: 0 | H2: 0 | I2: 0 | J2: 813779.8 | K2: 0 | L2: 0 | M2: 0 | N2: NaN
B3: Biogas | C3: 1642.892 | D3: 1642.892 | E3: 0 | F3: 0 | G3: 0 | H3: 0 | I3: 0 | J3: 3589718 | K3: 0 | L3: 0 | M3: 0 | N3: NaN
B4: Biomass | C4: 9185.807 | D4: 9185.807 | E4: 0 | F4: 0 | G4: 0 | H4: 0 | I4: 0 | J4: 20070990 | K4: 0 | L4: 0 | M4: 0 | N4: NaN
B5: Combined Cycle Gas Turbine | C5: 23586 | D5: 23586 | E5: 0 | F5: 0 | G5: 0 | H5: 0 | I5: 0 | J5: 51535410 | K5: 0 | L5: 0 | M5: 0 | N5: NaN
B6: Combined Heat & Power | C6: 3534.036 | D6: 3534.036 | E6: 0 | F6: 0 | G6: 0 | H6: 0 | I6: 0 | J6: 7721869 | K6: 0 | L6: 0 | M6: 0 | N6: NaN
B7: European Imports | C7: 13695 | D7: 13695 | E7: 3522451 | F7: 0 | G7: 3522451 | H7: 0 | I7: 0.1177149 | J7: 26401120 | K7: 0 | L7: 40227900 | M7: 40227900 | N7: 11.420431
B8: Gas Engine | C8: 4067.294 | D8: 4067.294 | E8: 0 | F8: 0 | G8: 0 | H8: 0 | I8: 0 | J8: 8887037 | K8: 0 | L8: 0 | M8: 0 | N8: NaN
B9: Geothermal | C9: 11 | D9: 11 | E9: 4564.679 | F9: 0 | G9: 4564.679 | H9: 0 | I9: 0.1899182 | J9: 19470.32 | K9: 0 | L9: 56875.9 | M9: 97976.78 | N9: 21.46409
B10: Landfill Gas | C10: 834.5111 | D10: 834.5111 | E10: 939.5542 | F10: 0 | G10: 939.5542 | H10: 0 | I10: 0.0005152718 | J10: 1822467 | K10: 0 | L10: 50735.92 | M10: 50908.45 | N10: 54.18386
B11: Large Hydro | C11: 1897.296 | D11: 1897.296 | E11: 1385678 | F11: 0 | G11: 1385678 | H11: 0 | I11: 0.3342534 | J11: 272558.8 | K11: 0 | L11: 0 | M11: 9492907 | N11: 6.850731
B12: Load Shedding | C12: 48629.19 | D12: 48629.19 | E12: 0 | F12: 0 | G12: 0 | H12: 0 | I12: 0 | J12: 52178340 | K12: 0 | L12: 0 | M12: 0 | N12: NaN
B13: Marine Energy | C13: 254.358 | D13: 254.358 | E13: 239212.9 | F13: 0 | G13: 239212.9 | H13: 0 | I13: 0.4304153 | J13: 34556.69 | K13: 0 | L13: 0 | M13: 1997884 | N13: 8.35191
B14: Nuclear | C14: 4570 | D14: 4570 | E14: 4052395 | F14: 0 | G14: 4052395 | H14: 0 | I14: 0.40583 | J14: 5933055 | K14: 0 | L14: 40523950 | M14: 67645010 | N14: 16.692602
B15: Offshore Wind | C15: 53544.2 | D15: 53544.2 | E15: 25297990 | F15: 0 | G15: 25297990 | H15: 0 | I15: 0.2162331 | J15: 6816858 | K15: 0 | L15: 0 | M15: 102337400 | N15: 4.045277
B16: Oil | C16: 78.5 | D16: 78.5 | E16: 0 | F16: 0 | G16: 0 | H16: 0 | I16: 0 | J16: 171522.5 | K16: 0 | L16: 0 | M16: 0 | N16: NaN
B17: Onshore Wind | C17: 27270.74 | D17: 27270.74 | E17: 11166210 | F17: 0 | G17: 11166210 | H17: 0 | I17: 0.1873947 | J17: 3168929 | K17: 0 | L17: 0 | M17: 42204570 | N17: 3.779669
B18: Open Cycle Gas Turbine | C18: 3662.89 | D18: 3662.89 | E18: 0 | F18: 0 | G18: 0 | H18: 0 | I18: 0 | J18: 8003415 | K18: 0 | L18: 0 | M18: 0 | N18: NaN
B19: Sewage Gas | C19: 55.81939 | D19: 55.81939 | E19: 0 | F19: 0 | G19: 0 | H19: 0 | I19: 0 | J19: 121965.4 | K19: 0 | L19: 0 | M19: 0 | N19: NaN
B20: Solar PV | C20: 40470.42 | D20: 40470.42 | E20: 13153100 | F20: 0 | G20: 13153100 | H20: 0 | I20: 0.1487438 | J20: 1412444 | K20: 0 | L20: 0 | M20: 90049560 | N20: 6.846263
B21: Waste to Energy | C21: 4643.178 | D21: 4643.178 | E21: 0 | F21: 0 | G21: 0 | H21: 0 | I21: 0 | J21: 10145340 | K21: 0 | L21: 0 | M21: 0 | N21: NaN
A22: Line | B22: AC | C22: 230800 | D22: 230800 | E22: 34980080 | F22: 21402270 | G22: 13577810 | H22: -13577810 | I22: 0.1118036 | J22: 0 | K22: 0 | L22: 0 | M22: 132119300 | N22: 2.343275
A23: Link | B23: DC | C23: 12450 | D23: 12450 | E23: 9507955 | F23: 5895185 | G23: 3612770 | H23: -3612770 | I23: 0.5662243 | J23: 30816020 | K23: 0 | L23: 0 | M23: 70048000 | N23: 4.547644
B24: DSM | C24: 26000000 | D24: 26000000 | E24: 0 | F24: 109040.9 | G24: -109040.9 | H24: 0 | I24: 1.919397e-06 | J24: 56809890000 | K24: 0 | L24: 1.09041 | M24: -807885.7 | N24: -7.409014
B25: Electrolysis | C25: 3653.095 | D25: 3653.095 | E25: 0 | F25: 136478.5 | G25: -136478.5 | H25: 0 | I25: 0.01709826 | J25: 7845534 | K25: 0 | L25: 0 | M25: 0 | N25: NaN
B26: H2 Power Generation | C26: 278.381 | D26: 278.381 | E26: 0 | F26: 91497.84 | G26: -91497.84 | H26: 0 | I26: 0.1504249 | J26: 516764.6 | K26: 0 | L26: 457489.2 | M26: 0 | N26: NaN
B27: Virtual Link | C27: 156000000 | D27: 156000000 | E27: 0 | F27: 16643.26 | G27: -16643.26 | H27: 16643.26 | I27: 4.882724e-08 | J27: 340860000000 | K27: 0 | L27: 0.16643 | M27: -90369.41 | N27: -5.429792
A28: Load | B28: Data Centre | C28: 0 | D28: 0 | E28: 0 | F28: 1877543 | G28: -1877543 | H28: 0 | I28: NaN | J28: 0 | K28: 0 | L28: 0 | M28: -14080300 | N28: -7.499323
B29: Electricity | C29: 0 | D29: 0 | E29: 0 | F29: 52178340 | G29: -52178340 | H29: 0 | I29: NaN | J29: 0 | K29: 0 | L29: 0 | M29: -410518000 | N29: -7.867595
A30: StorageUnit | B30: Battery Storage | C30: 26471.97 | D30: 26471.97 | E30: 3617944 | F30: 6804928 | G30: -3186985 | H30: 0 | I30: 0.1801979 | J30: 61028250 | K30: 0 | L30: 0 | M30: 16528890 | N30: 1.585829
B31: Domestic Battery Storage | C31: 857.708 | D31: 857.708 | E31: 182298.6 | F31: 300876.4 | G31: -118577.9 | H31: 0 | I31: 0.2578182 | J31: 1992670 | K31: 0 | L31: 0 | M31: 542221.3 | N31: 1.122205
B32: Liquid Air Energy Storage | C32: 457.994 | D32: 457.994 | E32: 33421.78 | F32: 239437.1 | G32: -206015.3 | H32: 0 | I32: 0.2726634 | J32: 1206732 | K32: 0 | L32: 0 | M32: 543258.3 | N32: 1.990986
B33: Pumped Storage Hydroelectricity | C33: 5300 | D33: 5300 | E33: 1068761 | F33: 2323427 | G33: -1254666 | H33: 0 | I33: 0.2929224 | J33: 12835170 | K33: 0 | L33: 0 | M33: 10364760 | N33: 3.05548
A34: Store | B34: DSM | C34: 13000000 | D34: 13000000 | E34: 54520.46 | F34: 54520.46 | G34: 0 | H34: 0 | I34: 0.9999265 | J34: 0 | K34: 0 | L34: 0 | M34: 0 | N34: NaN
B35: Hydrogen Gas | C35: 46768.01 | D35: 46768.01 | E35: 90325.05 | F35: 94362.16 | G35: -4037.109 | H35: 0 | I35: 0.3950665 | J35: 0 | K35: 0 | L35: 0 | M35: 0 | N35: NaN

Sheet CFE
C1: Optimal Capacity | D1: Installed Capacity | E1: Supply | F1: Withdrawal | G1: Energy Balance | H1: Transmission | I1: Capacity Factor | J1: Curtailment | K1: Capital Expenditure | L1: Operational Expenditure | M1: Revenue | N1: Market Value
A2: Generator | B2: Advanced Biofuel | C2: 372.43929 | D2: 372.43929 | E2: 0 | F2: 0 | G2: 0 | H2: 0 | I2: 0 | J2: 813779.8 | K2: 0 | L2: 0 | M2: 0 | N2: NaN
B3: Biogas | C3: 1642.8915 | D3: 1642.8915 | E3: 0 | F3: 0 | G3: 0 | H3: 0 | I3: 0 | J3: 3589718 | K3: 0 | L3: 0 | M3: 0 | N3: NaN
B4: Biomass | C4: 9185.8067 | D4: 9185.8067 | E4: 0 | F4: 0 | G4: 0 | H4: 0 | I4: 0 | J4: 20070990 | K4: 0 | L4: 0 | M4: 0 | N4: NaN
B5: Combined Cycle Gas Turbine | C5: 23586 | D5: 23586 | E5: 0 | F5: 0 | G5: 0 | H5: 0 | I5: 0 | J5: 51535410 | K5: 0 | L5: 0 | M5: 0 | N5: NaN
B6: Combined Heat & Power | C6: 3534.036 | D6: 3534.036 | E6: 0 | F6: 0 | G6: 0 | H6: 0 | I6: 0 | J6: 7721869 | K6: 0 | L6: 0 | M6: 0 | N6: NaN
B7: European Imports | C7: 13695 | D7: 13695 | E7: 3566755 | F7: 0 | G7: 3566755 | H7: 0 | I7: 0.119195 | J7: 26356820 | K7: 0 | L7: 40697210 | M7: 40697210 | N7: 11.41015
B8: Gas Engine | C8: 4067.294 | D8: 4067.294 | E8: 0 | F8: 0 | G8: 0 | H8: 0 | I8: 0 | J8: 8887037 | K8: 0 | L8: 0 | M8: 0 | N8: NaN
B9: Geothermal | C9: 11 | D9: 11 | E9: 4643.509 | F9: 0 | G9: 4643.509 | H9: 0 | I9: 0.193198 | J9: 19391.49 | K9: 0 | L9: 57858.12 | M9: 99256.85 | N9: 21.375356
B10: Landfill Gas | C10: 834.51107 | D10: 834.51107 | E10: 1327.783 | F10: 0 | G10: 1327.783 | H10: 0 | I10: 0.000728 | J10: 1822079 | K10: 0 | L10: 71700.3 | M10: 71876.93 | N10: 54.133129
B11: Large Hydro | C11: 1897.296 | D11: 1897.296 | E11: 1408171 | F11: 0 | G11: 1408171 | H11: 0 | I11: 0.339679 | J11: 250065.7 | K11: 0 | L11: 0 | M11: 9471836 | N11: 6.726339
B12: Load Shedding | C12: 48629.191 | D12: 48629.191 | E12: 0 | F12: 0 | G12: 0 | H12: 0 | I12: 0 | J12: 52178340 | K12: 0 | L12: 0 | M12: 0 | N12: NaN
B13: Marine Energy | C13: 254.358 | D13: 254.358 | E13: 240759.2 | F13: 0 | G13: 240759.2 | H13: 0 | I13: 0.433198 | J13: 33010.38 | K13: 0 | L13: 0 | M13: 2000389 | N13: 8.30867
B14: Nuclear | C14: 4570 | D14: 4570 | E14: 4061032 | F14: 0 | G14: 4061032 | H14: 0 | I14: 0.406695 | J14: 5924418 | K14: 0 | L14: 40610320 | M14: 68044500 | N14: 16.755471
B15: Offshore Wind | C15: 53544.202 | D15: 53544.202 | E15: 25568500 | F15: 0 | G15: 25568500 | H15: 0 | I15: 0.218545 | J15: 6546350 | K15: 0 | L15: 0 | M15: 102405100 | N15: 4.005128
B16: Oil | C16: 78.5 | D16: 78.5 | E16: 0 | F16: 0 | G16: 0 | H16: 0 | I16: 0 | J16: 171522.5 | K16: 0 | L16: 0 | M16: 0 | N16: NaN
B17: Onshore Wind | C17: 27270.741 | D17: 27270.741 | E17: 11218600 | F17: 0 | G17: 11218600 | H17: 0 | I17: 0.188274 | J17: 3116530 | K17: 0 | L17: 0 | M17: 42150350 | N17: 3.757183
B18: Open Cycle Gas Turbine | C18: 3662.89 | D18: 3662.89 | E18: 0 | F18: 0 | G18: 0 | H18: 0 | I18: 0 | J18: 8003415 | K18: 0 | L18: 0 | M18: 0 | N18: NaN
B19: Sewage Gas | C19: 55.81939 | D19: 55.81939 | E19: 0 | F19: 0 | G19: 0 | H19: 0 | I19: 0 | J19: 121965.4 | K19: 0 | L19: 0 | M19: 0 | N19: NaN
B20: Solar PV | C20: 40470.422 | D20: 40470.422 | E20: 13215940 | F20: 0 | G20: 13215940 | H20: 0 | I20: 0.149455 | J20: 1349598 | K20: 0 | L20: 0 | M20: 90278670 | N20: 6.831043
B21: Waste to Energy | C21: 4643.178 | D21: 4643.178 | E21: 0 | F21: 0 | G21: 0 | H21: 0 | I21: 0 | J21: 10145340 | K21: 0 | L21: 0 | M21: 0 | N21: NaN
A22: Line | B22: AC | C22: 230800 | D22: 230800 | E22: 35157820 | F22: 21433810 | G22: 13724010 | H22: -13724010 | I22: 0.112219 | J22: 0 | K22: 0 | L22: 0 | M22: 134350300 | N22: 2.37403
A23: Link | B23: DC | C23: 12450 | D23: 12450 | E23: 9519542 | F23: 5861332 | G23: 3658210 | H23: -3658210 | I23: 0.565406 | J23: 30861460 | K23: 0 | L23: 0 | M23: 70784100 | N23: 4.602086
B24: Electrolysis | C24: 3653.0948 | D24: 3653.0948 | E24: 0 | F24: 136224.8 | G24: -136224.8 | H24: 0 | I24: 0.017066 | J24: 7845787 | K24: 0 | L24: 0 | M24: 0 | N24: NaN
B25: H2 Power Generation | C25: 278.381 | D25: 278.381 | E25: 0 | F25: 87637.66 | G25: -87637.66 | H25: 0 | I25: 0.144079 | J25: 520624.8 | K25: 0 | L25: 438188.3 | M25: 0 | N25: NaN
A26: Load | B26: Data Centre | C26: 0 | D26: 0 | E26: 0 | F26: 1877543 | G26: -1877543 | H26: 0 | I26: NaN | J26: 0 | K26: 0 | L26: 0 | M26: -14118940 | N26: -7.519904
B27: Electricity | C27: 0 | D27: 0 | E27: 0 | F27: 52178340 | G27: -52178340 | H27: 0 | I27: NaN | J27: 0 | K27: 0 | L27: 0 | M27: -411891500 | N27: -7.893917
A28: StorageUnit | B28: Battery Storage | C28: 26471.973 | D28: 26471.973 | E28: 2416534 | F28: 5877705 | G28: -3461171 | H28: 0 | I28: 0.143397 | J28: 61302430 | K28: 0 | L28: 0 | M28: 16741690 | N28: 2.018472
B29: Domestic Battery Storage | C29: 857.708 | D29: 857.708 | E29: 128495.8 | F29: 261838 | G29: -133342.2 | H29: 0 | I29: 0.208279 | J29: 2007434 | K29: 0 | L29: 0 | M29: 548921.5 | N29: 1.406288
B30: Liquid Air Energy Storage | C30: 457.994 | D30: 457.994 | E30: 29950.11 | F30: 248405.2 | G30: -218455.1 | H30: 0 | I30: 0.278156 | J30: 1219172 | K30: 0 | L30: 0 | M30: 549749.4 | N30: 1.974991
B31: Pumped Storage Hydroelectricity | C31: 5300 | D31: 5300 | E31: 812898.6 | F31: 2228834 | G31: -1415935 | H31: 0 | I31: 0.26266 | J31: 12996440 | K31: 0 | L31: 0 | M31: 10545950 | N31: 3.467086
A32: Store | B32: Hydrogen Gas | C32: 46768.008 | D32: 46768.008 | E32: 86234.67 | F32: 93954.4 | G32: -7719.725 | H32: 0 | I32: 0.755443 | J32: 0 | K32: 0 | L32: 0 | M32: 0 | N32: NaN

Sheet CFE_both
C1: Optimal Capacity | D1: Installed Capacity | E1: Supply | F1: Withdrawal | G1: Energy Balance | H1: Transmission | I1: Capacity Factor | J1: Curtailment | K1: Capital Expenditure | L1: Operational Expenditure | M1: Revenue | N1: Market Value
A2: Generator | B2: Advanced Biofuel | C2: 372.4393 | D2: 372.4393 | E2: 0 | F2: 0 | G2: 0 | H2: 0 | I2: 0 | J2: 813779.8 | K2: 0 | L2: 0 | M2: 0 | N2: NaN
B3: Biogas | C3: 1642.892 | D3: 1642.892 | E3: 0 | F3: 0 | G3: 0 | H3: 0 | I3: 0 | J3: 3589718 | K3: 0 | L3: 0 | M3: 0 | N3: NaN
B4: Biomass | C4: 9185.807 | D4: 9185.807 | E4: 0 | F4: 0 | G4: 0 | H4: 0 | I4: 0 | J4: 20070990 | K4: 0 | L4: 0 | M4: 0 | N4: NaN
B5: Combined Cycle Gas Turbine | C5: 23586 | D5: 23586 | E5: 0 | F5: 0 | G5: 0 | H5: 0 | I5: 0 | J5: 51535410 | K5: 0 | L5: 0 | M5: 0 | N5: NaN
B6: Combined Heat & Power | C6: 3534.036 | D6: 3534.036 | E6: 0 | F6: 0 | G6: 0 | H6: 0 | I6: 0 | J6: 7721869 | K6: 0 | L6: 0 | M6: 0 | N6: NaN
B7: European Imports | C7: 13695 | D7: 13695 | E7: 3512719 | F7: 0 | G7: 3512719 | H7: 0 | I7: 0.1173897 | J7: 26410860 | K7: 0 | L7: 39740210 | M7: 39740210 | N7: 11.313233
B8: Gas Engine | C8: 4067.294 | D8: 4067.294 | E8: 0 | F8: 0 | G8: 0 | H8: 0 | I8: 0 | J8: 8887037 | K8: 0 | L8: 0 | M8: 0 | N8: NaN
B9: Geothermal | C9: 11 | D9: 11 | E9: 4564.679 | F9: 0 | G9: 4564.679 | H9: 0 | I9: 0.1899182 | J9: 19470.32 | K9: 0 | L9: 56875.9 | M9: 97186.44 | N9: 21.290948
B10: Landfill Gas | C10: 834.5111 | D10: 834.5111 | E10: 37.80596 | F10: 0 | G10: 37.80596 | H10: 0 | I10: 2.07307e-05 | J10: 1823369 | K10: 0 | L10: 2041.522 | M10: 2152.47 | N10: 56.942775
B11: Large Hydro | C11: 1897.296 | D11: 1897.296 | E11: 1397603 | F11: 0 | G11: 1397603 | H11: 0 | I11: 0.3371299 | J11: 260633.9 | K11: 0 | L11: 0 | M11: 9282304 | N11: 6.641589
B12: Load Shedding | C12: 48629.19 | D12: 48629.19 | E12: 0 | F12: 0 | G12: 0 | H12: 0 | I12: 0 | J12: 52178340 | K12: 0 | L12: 0 | M12: 0 | N12: NaN
B13: Marine Energy | C13: 254.358 | D13: 254.358 | E13: 239523.5 | F13: 0 | G13: 239523.5 | H13: 0 | I13: 0.4309741 | J13: 34246.1 | K13: 0 | L13: 0 | M13: 1973243 | N13: 8.238205
B14: Nuclear | C14: 4570 | D14: 4570 | E14: 4026737 | F14: 0 | G14: 4026737 | H14: 0 | I14: 0.4032604 | J14: 5958713 | K14: 0 | L14: 40267370 | M14: 67153380 | N14: 16.676875
B15: Offshore Wind | C15: 53544.2 | D15: 53544.2 | E15: 25259670 | F15: 0 | G15: 25259670 | H15: 0 | I15: 0.2159055 | J15: 6855179 | K15: 0 | L15: 0 | M15: 101261700 | N15: 4.008829
B16: Oil | C16: 78.5 | D16: 78.5 | E16: 0 | F16: 0 | G16: 0 | H16: 0 | I16: 0 | J16: 171522.5 | K16: 0 | L16: 0 | M16: 0 | N16: NaN
B17: Onshore Wind | C17: 27270.74 | D17: 27270.74 | E17: 11256640 | F17: 0 | G17: 11256640 | H17: 0 | I17: 0.1889123 | J17: 3078499 | K17: 0 | L17: 0 | M17: 41619570 | N17: 3.697337
B18: Open Cycle Gas Turbine | C18: 3662.89 | D18: 3662.89 | E18: 0 | F18: 0 | G18: 0 | H18: 0 | I18: 0 | J18: 8003415 | K18: 0 | L18: 0 | M18: 0 | N18: NaN
B19: Sewage Gas | C19: 55.81939 | D19: 55.81939 | E19: 0 | F19: 0 | G19: 0 | H19: 0 | I19: 0 | J19: 121965.4 | K19: 0 | L19: 0 | M19: 0 | N19: NaN
B20: Solar PV | C20: 40470.42 | D20: 40470.42 | E20: 13185300 | F20: 0 | G20: 13185300 | H20: 0 | I20: 0.149108 | J20: 1380241 | K20: 0 | L20: 0 | M20: 89510120 | N20: 6.788629
B21: Waste to Energy | C21: 4643.178 | D21: 4643.178 | E21: 0 | F21: 0 | G21: 0 | H21: 0 | I21: 0 | J21: 10145340 | K21: 0 | L21: 0 | M21: 0 | N21: NaN
A22: Line | B22: AC | C22: 230800 | D22: 230800 | E22: 34744710 | F22: 21585590 | G22: 13159120 | H22: -13159120 | I22: 0.1117004 | J22: 0 | K22: 0 | L22: 0 | M22: 128675900 | N22: 2.284311
A23: Link | B23: DC | C23: 12450 | D23: 12450 | E23: 9519372 | F23: 5916583 | G23: 3602789 | H23: -3602789 | I23: 0.5674306 | J23: 30806040 | K23: 0 | L23: 0 | M23: 69208700 | N23: 4.483604
B24: DSM | C24: 26000000 | D24: 26000000 | E24: 0 | F24: 167658.1 | G24: -167658.1 | H24: 0 | I24: 2.951207e-06 | J24: 56809830000 | K24: 0 | L24: 1.67658 | M24: -234292.9 | N24: -1.397445
B25: Electrolysis | C25: 3653.095 | D25: 3653.095 | E25: 0 | F25: 125107.8 | G25: -125107.8 | H25: 0 | I25: 0.01567371 | J25: 7856904 | K25: 0 | L25: 0 | M25: 0 | N25: NaN
B26: H2 Power Generation | C26: 278.381 | D26: 278.381 | E26: 0 | F26: 84067.95 | G26: -84067.95 | H26: 0 | I26: 0.13821 | J26: 524194.5 | K26: 0 | L26: 420339.7 | M26: 0 | N26: NaN
B27: Virtual Link | C27: 156000000 | D27: 156000000 | E27: 0 | F27: 16869.5 | G27: -16869.5 | H27: 16869.5 | I27: 4.949096e-08 | J27: 340860000000 | K27: 0 | L27: 0.16869 | M27: -33755.36 | N27: -2.000971
A28: Load | B28: Data Centre | C28: 0 | D28: 0 | E28: 0 | F28: 1877543 | G28: -1877543 | H28: 0 | I28: NaN | J28: 0 | K28: 0 | L28: 0 | M28: -13965940 | N28: -7.438414
B29: Electricity | C29: 0 | D29: 0 | E29: 0 | F29: 52178340 | G29: -52178340 | H29: 0 | I29: NaN | J29: 0 | K29: 0 | L29: 0 | M29: -407915500 | N29: -7.817717
A30: StorageUnit | B30: Battery Storage | C30: 26471.97 | D30: 26471.97 | E30: 3516495 | F30: 6738987 | G30: -3222492 | H30: 0 | I30: 0.1773039 | J30: 61063750 | K30: 0 | L30: 0 | M30: 16559150 | N30: 1.614663
B31: Domestic Battery Storage | C31: 857.708 | D31: 857.708 | E31: 180965.7 | F31: 300514.2 | G31: -119548.5 | H31: 0 | I31: 0.2569137 | J31: 1993641 | K31: 0 | L31: 0 | M31: 543364.6 | N31: 1.12853
B32: Liquid Air Energy Storage | C32: 457.994 | D32: 457.994 | E32: 33967.29 | F32: 242858.4 | G32: -208891.1 | H32: 0 | I32: 0.2766274 | J32: 1209608 | K32: 0 | L32: 0 | M32: 543975.7 | N32: 1.965047
B33: Pumped Storage Hydroelectricity | C33: 5300 | D33: 5300 | E33: 1031336 | F33: 2314309 | G33: -1282973 | H33: 0 | I33: 0.2889033 | J33: 12863470 | K33: 0 | L33: 0 | M33: 10310820 | N33: 3.081865
A34: Store | B34: DSM | C34: 13000000 | D34: 13000000 | E34: 83829.03 | F34: 83829.03 | G34: 0 | H34: 0 | I34: 0.9990929 | J34: 0 | K34: 0 | L34: 0 | M34: 0 | N34: NaN
B35: Hydrogen Gas | C35: 46768.01 | D35: 46768.01 | E35: 82619.88 | F35: 86127.37 | G35: -3507.494 | H35: 0 | I35: 0.343239 | J35: 0 | K35: 0 | L35: 0 | M35: 0 | N35: NaN
